powerbeatsvr/__init__.py
powerbeatsvr/__main__.py
powerbeatsvr/bs_lib.py
powerbeatsvr/reader.py
powerbeatsvr/writer.py
powerbeatsvr-0.3.0.dist-info/LICENSE
powerbeatsvr-0.3.0.dist-info/METADATA
powerbeatsvr-0.3.0.dist-info/WHEEL
powerbeatsvr-0.3.0.dist-info/entry_points.txt
powerbeatsvr-0.3.0.dist-info/top_level.txt
powerbeatsvr-0.3.0.dist-info/RECORD
