Metadata-Version: 2.1
Name: powerbeatsvr
Version: 0.3.0
Summary: Convert beats saber levels to PowerBeatsVR
Home-page: https://github.com/guysoft/PowerBeatsVR_song_writer
Author: Guy Sheffer
Author-email: gusyoft@gmail.com
License: GPLv3
Platform: UNKNOWN
Classifier: License :: OSI Approved :: MIT License
Classifier: Programming Language :: Python
Classifier: Programming Language :: Python :: 3
Requires-Dist: pyunpack
